markdown_up/__init__.py
markdown_up/__main__.py
markdown_up/api.py
markdown_up/app.py
markdown_up/main.py
markdown_up/static/__init__.py
markdown_up/static/index.html
markdown_up/static/markdownUpIndex.bare
markdown_up-2.6.1.dist-info/licenses/LICENSE
markdown_up-2.6.1.dist-info/METADATA
markdown_up-2.6.1.dist-info/WHEEL
markdown_up-2.6.1.dist-info/entry_points.txt
markdown_up-2.6.1.dist-info/top_level.txt
markdown_up-2.6.1.dist-info/RECORD
