Metadata-Version: 2.4
Name: markdown-up
Version: 2.6.1
Summary: MarkdownUp is a Markdown viewer
Home-page: https://github.com/craigahobbs/markdown-up-py
Author: Craig A. Hobbs
Author-email: craigahobbs@gmail.com
License: MIT
Keywords: Markdown,viewer
Classifier: Development Status :: 5 - Production/Stable
Classifier: Intended Audience :: Developers
Classifier: Operating System :: OS Independent
Classifier: Programming Language :: Python :: 3.10
Classifier: Programming Language :: Python :: 3.11
Classifier: Programming Language :: Python :: 3.12
Classifier: Programming Language :: Python :: 3.13
Classifier: Programming Language :: Python :: 3.14
Classifier: Topic :: Utilities
License-File: LICENSE
Requires-Dist: bare-script>=3.8.0
Requires-Dist: chisel>=1.9.0
Requires-Dist: waitress>=3.0.0
Dynamic: license-file
